aplabcolemen.py
aplabcolemen-0.0.2.dist-info/METADATA
aplabcolemen-0.0.2.dist-info/WHEEL
aplabcolemen-0.0.2.dist-info/top_level.txt
aplabcolemen-0.0.2.dist-info/RECORD
