Metadata-Version: 2.1
Name: aplabcolemen
Version: 0.0.2
Summary: aplabcolemen
Author: Colemen Atwood
Author-email: <atwoodcolemen@gmail.com>
Keywords: python
Classifier: Development Status :: 3 - Alpha
Classifier: Intended Audience :: Education
Classifier: Programming Language :: Python :: 2
Classifier: Programming Language :: Python :: 3
Classifier: Operating System :: MacOS :: MacOS X
Classifier: Operating System :: Microsoft :: Windows
